ksj/__init__.py
ksj/api.py
ksj/shapefile.py
ksj/translate.py
ksj-1.0.0.dist-info/METADATA
ksj-1.0.0.dist-info/WHEEL
ksj-1.0.0.dist-info/top_level.txt
ksj-1.0.0.dist-info/RECORD
