Metadata-Version: 2.1
Name: ksj
Version: 1.0.0
Summary: This library will make the Kokudo Suuchi Jouhou API easy to use.
Home-page: https://github.com/nigimitama/ksj
Author: Masayoshi Mita
Author-email: nigimitama16@gmail.com
License: MIT
Platform: UNKNOWN
Requires-Dist: lxml (>=4.4.0)
Requires-Dist: xmljson (>=0.2.0)
Requires-Dist: xlrd (>=1.2.0)
Requires-Dist: geopandas (>=0.6.0)
